setup.cfg
setup.py
bottle_healthcheck/__init__.py
bottle_healthcheck.egg-info/PKG-INFO
bottle_healthcheck.egg-info/SOURCES.txt
bottle_healthcheck.egg-info/dependency_links.txt
bottle_healthcheck.egg-info/not-zip-safe
bottle_healthcheck.egg-info/top_level.txt
tests/__init__.py
tests/test_unit/__init__.py
tests/test_unit/test_healthcheck.py