Metadata-Version: 1.1
Name: bottle-healthcheck
Version: 0.2.1
Summary: Adds healthcheck endpoints to Bottle apps
Home-page: https://github.com/iurisilvio/bottle-healthcheck
Author: Iuri de Silvio
Author-email: iurisilvio@gmail.com
License: MIT
Platform: any
Classifier: Development Status :: 5 - Production/Stable
Classifier: Environment :: Web Environment
Classifier: Framework :: Bottle
Classifier: Programming Language :: Python
